{"author": null, "title": "Hardline North Korean general to meet Pompeo in New York", "description": "US secretary of state\u2019s talks offer hope that Trump-Kim June summit may still go ahead", "url": "https://www.ft.com/content/eb555e16-63e3-11e8-90c2-9563a0613e56", "urlToImage": "https://www.ft.com/__origami/service/image/v2/images/raw/http%3A%2F%2Fprod-upp-image-read.ft.com%2F27b5baa2-63eb-11e8-bdd1-cc0534df682c?source=next-opengraph&fit=scale-down&width=900", "publishedAt": null, "clasificare": {"general": 0.13319695188796535, "technology": 0.23516135930900794, "sports": 0.21195322724387056, "business": 0.10238524742327024, "entertainment": 0.20585233696683125, "science": 0.22551518858329406}}