{"author": null, "title": "US regulators propose major overhaul of Volcker rule", "description": "Changes will soothe bank grievances and cut back on reforms after last financial crisis", "url": "https://www.ft.com/content/2536a362-6437-11e8-90c2-9563a0613e56", "urlToImage": "https://www.ft.com/__origami/service/image/v2/images/raw/http%3A%2F%2Fprod-upp-image-read.ft.com%2F00408c86-643b-11e8-bdd1-cc0534df682c?source=next-opengraph&fit=scale-down&width=900", "publishedAt": null, "clasificare": {"general": 0.13879625512786264, "technology": 0.1782405130101739, "sports": 0.23104322581819614, "business": 0.20995356441360383, "entertainment": 0.16450879707663796, "science": 0.17850308934342027}}