{"author": "James Marson", "title": "\u2018Murdered\u2019 Russian Journalist Arkady Babchenko Is Alive, Explains Sting Operation to Lure Assassins", "description": "A Russian journalist and Kremlin critic reported killed late Tuesday appeared alive and well Wednesday to describe his part in what Ukrainian officials called an operation to catch a would-be murderer.", "url": "https://www.wsj.com/articles/russian-journalist-shows-up-to-dispel-reports-of-his-own-murder-1527697282", "urlToImage": "https://si.wsj.net/public/resources/images/B3-AP702_UKMURD_SOC_20180530121340.jpg", "publishedAt": "2018-05-30T16:21:00Z", "clasificare": {"general": 0.15148541262510049, "technology": 0.16126524001383336, "sports": 0.2464446900558484, "business": 0.18686677353231607, "entertainment": 0.25484809985681584, "science": 0.32603398468813966}}