{"author": "Casey Newton", "title": "Why New York beats Silicon Valley as a destination for some  startups", "description": "In the second episode of Converge with Casey Newton, Zola co-founder and CEO Shan-Lyn Ma tells us why New York is an ideal place to found a startup for new founders.", "url": "https://www.theverge.com/2018/5/30/17406594/zola-ceo-shan-lyn-ma-interview-converge-podcast", "urlToImage": "https://cdn.vox-cdn.com/thumbor/HSIj_JX18HJw9Ks6fSvhCQcKwvg=/0x146:2040x1214/fit-in/1200x630/cdn.vox-cdn.com/uploads/chorus_asset/file/11129895/converge_ep01_guest_0001.jpg", "publishedAt": "2018-05-30T11:30:02Z", "clasificare": {"general": 0.06902806206111153, "technology": 0.12218264273567458, "sports": 0.16179321698040444, "business": 0.09790899775954995, "entertainment": 0.22370583995916302, "science": 0.20436597154168565}}