{"author": "Ryan Sidle", "title": "Gianluigi Buffon Set To Sign Two Year Deal With PSG", "description": "The Italian legend finished with Juventus at the end of the season but will join the Ligue 1 champions rather than retire.", "url": "http://www.thesportbible.com/football/transfers-legends-gianluigi-buffon-set-to-sign-two-year-deal-with-psg-20180530", "urlToImage": "http://beta.ems.ladbiblegroup.com/s3/content/808x455/7a7cfb635b0ec1e8c74ba37752d257c6.png", "publishedAt": "2018-05-30T10:51:08Z", "clasificare": {"general": 0.10391989889477914, "technology": 0.15083656117774552, "sports": 0.171098777204676, "business": 0.13932464599875566, "entertainment": 0.21978169524509805, "science": 0.27454268160596723}}