{"author": null, "title": "ICC cricket committee saves the toss", "description": "After a two-day meeting in Mumbai, it also suggested that ball-tampering and personal abuse should carry serious penalties", "url": "http://www.espncricinfo.com/story/_/id/23641173/icc-cricket-committee-saves-toss", "urlToImage": "http://a3.espncdn.com/combiner/i?img=%2Fi%2Fcricket%2Fcricinfo%2F1080839_1296x729.jpg", "publishedAt": "2018-05-29T10:29:20Z", "clasificare": {"general": 0.1462224258911773, "technology": 0.17798380728953128, "sports": 0.1536236837411887, "business": 0.262172895366955, "entertainment": 0.18899784460915298, "science": 0.1082174552222187}}