{"author": "FourFourTwo", "title": "J. League apologises for bogus Torres transfer story", "description": "Fernando Torres appeared to have signed for Sagan Tosu but the J.League has confirmed the transfer announcement was made in error.", "url": "http://www.fourfourtwo.com/news/j-league-apologises-bogus-torres-transfer-story", "urlToImage": "https://images.cdn.fourfourtwo.com/sites/fourfourtwo.com/files/fernando-torres-cropped_1ns7s49ic9yao1dr5lfujko3jr.jpg", "publishedAt": "2018-05-30T17:31:01Z", "clasificare": {"general": 0.13534966270434381, "technology": 0.18578301482705825, "sports": 0.21048610041949778, "business": 0.17057161673531618, "entertainment": 0.23013528828471386, "science": 0.3001206147542308}}